sig2srv/__init__.py
sig2srv/asynchelper.py
sig2srv/cli.py
sig2srv/logging.py
sig2srv/sig2srv.py
sig2srv-0.1.1.dist-info/top_level.txt
sig2srv-0.1.1.dist-info/entry_points.txt
sig2srv-0.1.1.dist-info/METADATA
sig2srv-0.1.1.dist-info/DESCRIPTION.rst
sig2srv-0.1.1.dist-info/metadata.json
sig2srv-0.1.1.dist-info/WHEEL
sig2srv-0.1.1.dist-info/RECORD
