Metadata-Version: 2.0
Name: sig2srv
Version: 0.1.1
Summary: sig2srv converts incoming signals into suitable service(8) commands.
Home-page: https://github.com/astralblue/sig2srv
Author: Eugene M. Kim
Author-email: astralblue@gmail.com
License: MIT license
Keywords: sig2srv
Platform: UNKNOWN
Classifier: Development Status :: 2 - Pre-Alpha
Classifier: Intended Audience :: Developers
Classifier: License :: OSI Approved :: MIT License
Classifier: Natural Language :: English
Classifier: Programming Language :: Python :: 3.4
Classifier: Programming Language :: Python :: 3.5
Classifier: Programming Language :: Python :: 3.6
Requires-Dist: ctorrepr
